Owl-0.2.1.dist-info/DESCRIPTION.rst
Owl-0.2.1.dist-info/METADATA
Owl-0.2.1.dist-info/RECORD
Owl-0.2.1.dist-info/WHEEL
Owl-0.2.1.dist-info/metadata.json
Owl-0.2.1.dist-info/top_level.txt
owl/__init__.py
owl/api.py
owl/response_wrapper.py
