Metadata-Version: 1.1
Name: Owl
Version: 0.2.1
Summary: Monitor Falcon with Riemann
Home-page: https://github.com/merry-bits/Owl
Author: merry-bits
Author-email: merry-bits@users.noreply.github.com
License: GPLv2
Keywords: flacon riemann monitoring measure request time end-point duration
Platform: UNKNOWN
Classifier: Development Status :: 5 - Production/Stable
Classifier: Intended Audience :: Developers
Classifier: Topic :: System :: Monitoring
Classifier: Natural Language :: English
Classifier: License :: OSI Approved :: GNU General Public License v2 (GPLv2)
Classifier: Programming Language :: Python :: 2.7
Classifier: Programming Language :: Python :: 3.3
Classifier: Programming Language :: Python :: 3.4
Classifier: Programming Language :: Python :: 3.5
